nnlib/__init__.py
nnlib/l_layer/__init__.py
nnlib/l_layer/backward.py
nnlib/l_layer/forward.py
nnlib/utils/__init__.py
nnlib/utils/activation.py
nnlib/utils/cost.py
nnlib/utils/derivative.py
nnlib/utils/initialize.py
nnlib/utils/update.py
nnlib-0.2.dist-info/METADATA
nnlib-0.2.dist-info/RECORD
nnlib-0.2.dist-info/WHEEL
nnlib-0.2.dist-info/top_level.txt
